invenio_files_multisum_storage/__init__.py
invenio_files_multisum_storage/checksums.py
invenio_files_multisum_storage/config.py
invenio_files_multisum_storage/ext.py
invenio_files_multisum_storage/storage.py
invenio_files_multisum_storage/version.py
invenio_files_multisum_storage-1.0.4.dist-info/AUTHORS.rst
invenio_files_multisum_storage-1.0.4.dist-info/LICENSE
invenio_files_multisum_storage-1.0.4.dist-info/METADATA
invenio_files_multisum_storage-1.0.4.dist-info/WHEEL
invenio_files_multisum_storage-1.0.4.dist-info/entry_points.txt
invenio_files_multisum_storage-1.0.4.dist-info/top_level.txt
invenio_files_multisum_storage-1.0.4.dist-info/RECORD
